setup.py
pykachu/__init__.py
pykachu.egg-info/PKG-INFO
pykachu.egg-info/SOURCES.txt
pykachu.egg-info/dependency_links.txt
pykachu.egg-info/requires.txt
pykachu.egg-info/top_level.txt