Metadata-Version: 1.0
Name: pykachu
Version: 0.1.2
Summary: Monitoramento simples de tarefas em background usando Redis como backend 
Home-page: https://github.com/sievetech/pykachu
Author: Sieve
Author-email: sievetech@sieve.com.br
License: 3-BSD
Platform: UNKNOWN
